inventree_zebra/__init__.py
inventree_zebra/core.py
inventree_zebra-0.1.1.dist-info/licenses/LICENSE
inventree_zebra-0.1.1.dist-info/METADATA
inventree_zebra-0.1.1.dist-info/WHEEL
inventree_zebra-0.1.1.dist-info/entry_points.txt
inventree_zebra-0.1.1.dist-info/top_level.txt
inventree_zebra-0.1.1.dist-info/RECORD
