Metadata-Version: 2.4
Name: inventree-zebra
Version: 0.1.1
Summary: InvenTree Zebra driver for label printing support
Author-email: wolflu05 <76838159+wolflu05@users.noreply.github.com>
License-Expression: GPL-3.0+
Project-URL: Homepage, https://github.com/wolflu05/inventree-zebra
Keywords: inventree,plugin
Classifier: Programming Language :: Python :: 3
Classifier: Operating System :: OS Independent
Classifier: Framework :: InvenTree
Requires-Python: >=3.9
License-File: LICENSE
Requires-Dist: zpl==0.1.12
Dynamic: license-file
